{"domain":"zlypher.github.io","prodId":"//Zlypher//LOL Events//EN","name":"LCS","timezone":"UTC","events":[{"id":579005,"uid":579005,"sequence":1,"start":"2021-01-17T21:00:00.000Z","end":"2021-01-17T22:00:00.000Z","timezone":"UTC","stamp":"2021-01-17T21:00:00.000Z","timestamp":"2021-01-17T21:00:00.000Z","summary":"IMT vs C9","attendees":[],"alarms":[],"categories":[]},{"id":579006,"uid":579006,"sequence":1,"start":"2021-01-17T22:00:00.000Z","end":"2021-01-17T23:00:00.000Z","timezone":"UTC","stamp":"2021-01-17T22:00:00.000Z","timestamp":"2021-01-17T22:00:00.000Z","summary":"TL vs 100","attendees":[],"alarms":[],"categories":[]},{"id":579007,"uid":579007,"sequence":1,"start":"2021-01-17T23:00:00.000Z","end":"2021-01-18T00:00:00.000Z","timezone":"UTC","stamp":"2021-01-17T23:00:00.000Z","timestamp":"2021-01-17T23:00:00.000Z","summary":"DIG vs EG","attendees":[],"alarms":[],"categories":[]},{"id":579008,"uid":579008,"sequence":1,"start":"2021-01-18T00:00:00.000Z","end":"2021-01-18T01:00:00.000Z","timezone":"UTC","stamp":"2021-01-18T00:00:00.000Z","timestamp":"2021-01-18T00:00:00.000Z","summary":"CLG vs TSM","attendees":[],"alarms":[],"categories":[]},{"id":579009,"uid":579009,"sequence":1,"start":"2021-01-18T01:00:00.000Z","end":"2021-01-18T02:00:00.000Z","timezone":"UTC","stamp":"2021-01-18T01:00:00.000Z","timestamp":"2021-01-18T01:00:00.000Z","summary":"GG vs TL","attendees":[],"alarms":[],"categories":[]},{"id":579010,"uid":579010,"sequence":1,"start":"2021-01-22T23:00:00.000Z","end":"2021-01-23T00:00:00.000Z","timezone":"UTC","stamp":"2021-01-22T23:00:00.000Z","timestamp":"2021-01-22T23:00:00.000Z","summary":"DIG vs C9","attendees":[],"alarms":[],"categories":[]},{"id":579011,"uid":579011,"sequence":1,"start":"2021-01-23T00:00:00.000Z","end":"2021-01-23T01:00:00.000Z","timezone":"UTC","stamp":"2021-01-23T00:00:00.000Z","timestamp":"2021-01-23T00:00:00.000Z","summary":"GG vs 100","attendees":[],"alarms":[],"categories":[]},{"id":579012,"uid":579012,"sequence":1,"start":"2021-01-23T01:00:00.000Z","end":"2021-01-23T02:00:00.000Z","timezone":"UTC","stamp":"2021-01-23T01:00:00.000Z","timestamp":"2021-01-23T01:00:00.000Z","summary":"EG vs FLY","attendees":[],"alarms":[],"categories":[]},{"id":579013,"uid":579013,"sequence":1,"start":"2021-01-23T02:00:00.000Z","end":"2021-01-23T03:00:00.000Z","timezone":"UTC","stamp":"2021-01-23T02:00:00.000Z","timestamp":"2021-01-23T02:00:00.000Z","summary":"TL vs TSM","attendees":[],"alarms":[],"categories":[]},{"id":579014,"uid":579014,"sequence":1,"start":"2021-01-23T03:00:00.000Z","end":"2021-01-23T04:00:00.000Z","timezone":"UTC","stamp":"2021-01-23T03:00:00.000Z","timestamp":"2021-01-23T03:00:00.000Z","summary":"IMT vs FLY","attendees":[],"alarms":[],"categories":[]},{"id":579015,"uid":579015,"sequence":1,"start":"2021-01-23T21:00:00.000Z","end":"2021-01-24T00:00:00.000Z","timezone":"UTC","stamp":"2021-01-23T21:00:00.000Z","timestamp":"2021-01-23T21:00:00.000Z","summary":"Quarterfinal: TBD vs TBD","attendees":[],"alarms":[],"categories":[]},{"id":579016,"uid":579016,"sequence":1,"start":"2021-01-24T01:00:00.000Z","end":"2021-01-24T04:00:00.000Z","timezone":"UTC","stamp":"2021-01-24T01:00:00.000Z","timestamp":"2021-01-24T01:00:00.000Z","summary":"Quarterfinal: TBD vs TBD","attendees":[],"alarms":[],"categories":[]},{"id":579017,"uid":579017,"sequence":1,"start":"2021-01-24T21:00:00.000Z","end":"2021-01-25T00:00:00.000Z","timezone":"UTC","stamp":"2021-01-24T21:00:00.000Z","timestamp":"2021-01-24T21:00:00.000Z","summary":"Quarterfinal: TBD vs TBD","attendees":[],"alarms":[],"categories":[]},{"id":579018,"uid":579018,"sequence":1,"start":"2021-01-25T01:00:00.000Z","end":"2021-01-25T04:00:00.000Z","timezone":"UTC","stamp":"2021-01-25T01:00:00.000Z","timestamp":"2021-01-25T01:00:00.000Z","summary":"Quarterfinal: TBD vs TBD","attendees":[],"alarms":[],"categories":[]},{"id":579019,"uid":579019,"sequence":1,"start":"2021-01-29T23:00:00.000Z","end":"2021-01-30T04:00:00.000Z","timezone":"UTC","stamp":"2021-01-29T23:00:00.000Z","timestamp":"2021-01-29T23:00:00.000Z","summary":"Semifinal: TBD vs TBD","attendees":[],"alarms":[],"categories":[]},{"id":579020,"uid":579020,"sequence":1,"start":"2021-01-30T21:00:00.000Z","end":"2021-01-31T02:00:00.000Z","timezone":"UTC","stamp":"2021-01-30T21:00:00.000Z","timestamp":"2021-01-30T21:00:00.000Z","summary":"Semifinal: TBD vs TBD","attendees":[],"alarms":[],"categories":[]},{"id":579021,"uid":579021,"sequence":1,"start":"2021-01-31T21:00:00.000Z","end":"2021-02-01T02:00:00.000Z","timezone":"UTC","stamp":"2021-01-31T21:00:00.000Z","timestamp":"2021-01-31T21:00:00.000Z","summary":"Grand Final: TBD vs TBD","attendees":[],"alarms":[],"categories":[]}]}