{"domain":"zlypher.github.io","prodId":"//Zlypher//LOL Events//EN","name":"PCS","timezone":"UTC","events":[{"id":602948,"uid":602948,"sequence":1,"start":"2021-08-14T09:00:00.000Z","end":"2021-08-14T14:00:00.000Z","timezone":"UTC","stamp":"2021-08-14T09:00:00.000Z","timestamp":"2021-08-14T09:00:00.000Z","summary":"Round 2 Match 1: PSG vs JT","attendees":[],"alarms":[],"categories":[]},{"id":602949,"uid":602949,"sequence":1,"start":"2021-08-15T09:00:00.000Z","end":"2021-08-15T14:00:00.000Z","timezone":"UTC","stamp":"2021-08-15T09:00:00.000Z","timestamp":"2021-08-15T09:00:00.000Z","summary":"Round 2 Match 2: BYG vs MCX","attendees":[],"alarms":[],"categories":[]},{"id":602950,"uid":602950,"sequence":1,"start":"2021-08-20T09:00:00.000Z","end":"2021-08-20T14:00:00.000Z","timezone":"UTC","stamp":"2021-08-20T09:00:00.000Z","timestamp":"2021-08-20T09:00:00.000Z","summary":"Round 2 Match 3: TBD vs TBD","attendees":[],"alarms":[],"categories":[]},{"id":602951,"uid":602951,"sequence":1,"start":"2021-08-21T09:00:00.000Z","end":"2021-08-21T14:00:00.000Z","timezone":"UTC","stamp":"2021-08-21T09:00:00.000Z","timestamp":"2021-08-21T09:00:00.000Z","summary":"Round 2Match 4: TBD vs TBD","attendees":[],"alarms":[],"categories":[]},{"id":602952,"uid":602952,"sequence":1,"start":"2021-08-22T09:00:00.000Z","end":"2021-08-22T14:00:00.000Z","timezone":"UTC","stamp":"2021-08-22T09:00:00.000Z","timestamp":"2021-08-22T09:00:00.000Z","summary":"Round 3: TBD vs TBD","attendees":[],"alarms":[],"categories":[]},{"id":602953,"uid":602953,"sequence":1,"start":"2021-08-27T09:00:00.000Z","end":"2021-08-27T14:00:00.000Z","timezone":"UTC","stamp":"2021-08-27T09:00:00.000Z","timestamp":"2021-08-27T09:00:00.000Z","summary":"Round 4 Match 1: TBD vs TBD","attendees":[],"alarms":[],"categories":[]},{"id":602954,"uid":602954,"sequence":1,"start":"2021-08-28T09:00:00.000Z","end":"2021-08-28T14:00:00.000Z","timezone":"UTC","stamp":"2021-08-28T09:00:00.000Z","timestamp":"2021-08-28T09:00:00.000Z","summary":"Round 4 Match 2: TBD vs TBD","attendees":[],"alarms":[],"categories":[]},{"id":602955,"uid":602955,"sequence":1,"start":"2021-08-29T09:00:00.000Z","end":"2021-08-29T14:00:00.000Z","timezone":"UTC","stamp":"2021-08-29T09:00:00.000Z","timestamp":"2021-08-29T09:00:00.000Z","summary":"Finals: TBD vs TBD","attendees":[],"alarms":[],"categories":[]}]}