{"domain":"zlypher.github.io","prodId":"//Zlypher//LOL Events//EN","name":"Intel Arabian Cup","timezone":"UTC","events":[{"id":634159,"uid":634159,"sequence":1,"start":"2022-05-27T16:00:00.000Z","end":"2022-05-27T17:00:00.000Z","timezone":"UTC","stamp":"2022-05-27T16:00:00.000Z","timestamp":"2022-05-27T16:00:00.000Z","summary":"Thunderclouds E-Sports vs Fox Gaming","attendees":[],"alarms":[],"categories":[]},{"id":634163,"uid":634163,"sequence":1,"start":"2022-05-27T17:00:00.000Z","end":"2022-05-27T18:00:00.000Z","timezone":"UTC","stamp":"2022-05-27T17:00:00.000Z","timestamp":"2022-05-27T17:00:00.000Z","summary":"The Black Lotus vs RA'AD","attendees":[],"alarms":[],"categories":[]},{"id":634164,"uid":634164,"sequence":1,"start":"2022-05-27T18:00:00.000Z","end":"2022-05-27T19:00:00.000Z","timezone":"UTC","stamp":"2022-05-27T18:00:00.000Z","timestamp":"2022-05-27T18:00:00.000Z","summary":"Anubis Gaming vs Lost Esports","attendees":[],"alarms":[],"categories":[]},{"id":634166,"uid":634166,"sequence":1,"start":"2022-05-27T19:00:00.000Z","end":"2022-05-27T20:00:00.000Z","timezone":"UTC","stamp":"2022-05-27T19:00:00.000Z","timestamp":"2022-05-27T19:00:00.000Z","summary":"3BL Esports vs VSlash GnG","attendees":[],"alarms":[],"categories":[]},{"id":634168,"uid":634168,"sequence":1,"start":"2022-05-27T20:00:00.000Z","end":"2022-05-27T21:00:00.000Z","timezone":"UTC","stamp":"2022-05-27T20:00:00.000Z","timestamp":"2022-05-27T20:00:00.000Z","summary":"Geekay vs Nigma Galaxy Male","attendees":[],"alarms":[],"categories":[]},{"id":634170,"uid":634170,"sequence":1,"start":"2022-05-28T16:00:00.000Z","end":"2022-05-28T17:00:00.000Z","timezone":"UTC","stamp":"2022-05-28T16:00:00.000Z","timestamp":"2022-05-28T16:00:00.000Z","summary":"3BL Esports vs Lost Esports","attendees":[],"alarms":[],"categories":[]},{"id":634171,"uid":634171,"sequence":1,"start":"2022-05-28T17:00:00.000Z","end":"2022-05-28T18:00:00.000Z","timezone":"UTC","stamp":"2022-05-28T17:00:00.000Z","timestamp":"2022-05-28T17:00:00.000Z","summary":"Thunderclouds E-Sports vs RA'AD","attendees":[],"alarms":[],"categories":[]},{"id":634172,"uid":634172,"sequence":1,"start":"2022-05-28T18:00:00.000Z","end":"2022-05-28T19:00:00.000Z","timezone":"UTC","stamp":"2022-05-28T18:00:00.000Z","timestamp":"2022-05-28T18:00:00.000Z","summary":"Geekay vs VSlash GnG","attendees":[],"alarms":[],"categories":[]},{"id":634173,"uid":634173,"sequence":1,"start":"2022-05-28T19:00:00.000Z","end":"2022-05-28T20:00:00.000Z","timezone":"UTC","stamp":"2022-05-28T19:00:00.000Z","timestamp":"2022-05-28T19:00:00.000Z","summary":"Nigma Galaxy Male vs Fox Gaming","attendees":[],"alarms":[],"categories":[]},{"id":634174,"uid":634174,"sequence":1,"start":"2022-05-28T20:00:00.000Z","end":"2022-05-28T21:00:00.000Z","timezone":"UTC","stamp":"2022-05-28T20:00:00.000Z","timestamp":"2022-05-28T20:00:00.000Z","summary":"Anubis Gaming vs The Black Lotus","attendees":[],"alarms":[],"categories":[]},{"id":634175,"uid":634175,"sequence":1,"start":"2022-05-29T16:00:00.000Z","end":"2022-05-29T17:00:00.000Z","timezone":"UTC","stamp":"2022-05-29T16:00:00.000Z","timestamp":"2022-05-29T16:00:00.000Z","summary":"Thunderclouds E-Sports vs Anubis Gaming","attendees":[],"alarms":[],"categories":[]},{"id":634176,"uid":634176,"sequence":1,"start":"2022-05-29T17:00:00.000Z","end":"2022-05-29T18:00:00.000Z","timezone":"UTC","stamp":"2022-05-29T17:00:00.000Z","timestamp":"2022-05-29T17:00:00.000Z","summary":"Nigma Galaxy Male vs RA'AD","attendees":[],"alarms":[],"categories":[]},{"id":634177,"uid":634177,"sequence":1,"start":"2022-05-29T18:00:00.000Z","end":"2022-05-29T19:00:00.000Z","timezone":"UTC","stamp":"2022-05-29T18:00:00.000Z","timestamp":"2022-05-29T18:00:00.000Z","summary":"VSlash GnG vs Lost Esports","attendees":[],"alarms":[],"categories":[]},{"id":634178,"uid":634178,"sequence":1,"start":"2022-05-29T19:00:00.000Z","end":"2022-05-29T20:00:00.000Z","timezone":"UTC","stamp":"2022-05-29T19:00:00.000Z","timestamp":"2022-05-29T19:00:00.000Z","summary":"3BL Esports vs The Black Lotus","attendees":[],"alarms":[],"categories":[]},{"id":634179,"uid":634179,"sequence":1,"start":"2022-05-29T20:00:00.000Z","end":"2022-05-29T21:00:00.000Z","timezone":"UTC","stamp":"2022-05-29T20:00:00.000Z","timestamp":"2022-05-29T20:00:00.000Z","summary":"Geekay vs Fox Gaming","attendees":[],"alarms":[],"categories":[]},{"id":634180,"uid":634180,"sequence":1,"start":"2022-06-03T16:00:00.000Z","end":"2022-06-03T17:00:00.000Z","timezone":"UTC","stamp":"2022-06-03T16:00:00.000Z","timestamp":"2022-06-03T16:00:00.000Z","summary":"3BL Esports vs Thunderclouds E-Sports","attendees":[],"alarms":[],"categories":[]},{"id":634186,"uid":634186,"sequence":1,"start":"2022-06-03T17:00:00.000Z","end":"2022-06-03T18:00:00.000Z","timezone":"UTC","stamp":"2022-06-03T17:00:00.000Z","timestamp":"2022-06-03T17:00:00.000Z","summary":"Nigma Galaxy Male vs Anubis Gaming","attendees":[],"alarms":[],"categories":[]},{"id":634187,"uid":634187,"sequence":1,"start":"2022-06-03T18:00:00.000Z","end":"2022-06-03T19:00:00.000Z","timezone":"UTC","stamp":"2022-06-03T18:00:00.000Z","timestamp":"2022-06-03T18:00:00.000Z","summary":"Fox Gaming vs RA'AD","attendees":[],"alarms":[],"categories":[]},{"id":634188,"uid":634188,"sequence":1,"start":"2022-06-03T19:00:00.000Z","end":"2022-06-03T20:00:00.000Z","timezone":"UTC","stamp":"2022-06-03T19:00:00.000Z","timestamp":"2022-06-03T19:00:00.000Z","summary":"Geekay vs Lost Esports","attendees":[],"alarms":[],"categories":[]},{"id":634189,"uid":634189,"sequence":1,"start":"2022-06-03T20:00:00.000Z","end":"2022-06-03T21:00:00.000Z","timezone":"UTC","stamp":"2022-06-03T20:00:00.000Z","timestamp":"2022-06-03T20:00:00.000Z","summary":"VSlash GnG vs The Black Lotus","attendees":[],"alarms":[],"categories":[]},{"id":634192,"uid":634192,"sequence":1,"start":"2022-06-04T16:00:00.000Z","end":"2022-06-04T17:00:00.000Z","timezone":"UTC","stamp":"2022-06-04T16:00:00.000Z","timestamp":"2022-06-04T16:00:00.000Z","summary":"Nigma Galaxy Male vs 3BL Esports","attendees":[],"alarms":[],"categories":[]},{"id":634194,"uid":634194,"sequence":1,"start":"2022-06-04T17:00:00.000Z","end":"2022-06-04T18:00:00.000Z","timezone":"UTC","stamp":"2022-06-04T17:00:00.000Z","timestamp":"2022-06-04T17:00:00.000Z","summary":"VSlash GnG vs Thunderclouds E-Sports","attendees":[],"alarms":[],"categories":[]},{"id":634195,"uid":634195,"sequence":1,"start":"2022-06-04T18:00:00.000Z","end":"2022-06-04T19:00:00.000Z","timezone":"UTC","stamp":"2022-06-04T18:00:00.000Z","timestamp":"2022-06-04T18:00:00.000Z","summary":"Lost Esports vs The Black Lotus","attendees":[],"alarms":[],"categories":[]},{"id":634197,"uid":634197,"sequence":1,"start":"2022-06-04T19:00:00.000Z","end":"2022-06-04T20:00:00.000Z","timezone":"UTC","stamp":"2022-06-04T19:00:00.000Z","timestamp":"2022-06-04T19:00:00.000Z","summary":"Geekay vs RA'AD","attendees":[],"alarms":[],"categories":[]},{"id":634198,"uid":634198,"sequence":1,"start":"2022-06-04T20:00:00.000Z","end":"2022-06-04T21:00:00.000Z","timezone":"UTC","stamp":"2022-06-04T20:00:00.000Z","timestamp":"2022-06-04T20:00:00.000Z","summary":"Fox Gaming vs Anubis Gaming","attendees":[],"alarms":[],"categories":[]},{"id":634200,"uid":634200,"sequence":1,"start":"2022-06-05T16:00:00.000Z","end":"2022-06-05T17:00:00.000Z","timezone":"UTC","stamp":"2022-06-05T16:00:00.000Z","timestamp":"2022-06-05T16:00:00.000Z","summary":"VSlash GnG vs Nigma Galaxy Male","attendees":[],"alarms":[],"categories":[]},{"id":634202,"uid":634202,"sequence":1,"start":"2022-06-05T17:00:00.000Z","end":"2022-06-05T18:00:00.000Z","timezone":"UTC","stamp":"2022-06-05T17:00:00.000Z","timestamp":"2022-06-05T17:00:00.000Z","summary":"Lost Esports vs Thunderclouds E-Sports","attendees":[],"alarms":[],"categories":[]},{"id":634208,"uid":634208,"sequence":1,"start":"2022-06-05T18:00:00.000Z","end":"2022-06-05T19:00:00.000Z","timezone":"UTC","stamp":"2022-06-05T18:00:00.000Z","timestamp":"2022-06-05T18:00:00.000Z","summary":"Fox Gaming vs 3BL Esports","attendees":[],"alarms":[],"categories":[]},{"id":634209,"uid":634209,"sequence":1,"start":"2022-06-05T19:00:00.000Z","end":"2022-06-05T20:00:00.000Z","timezone":"UTC","stamp":"2022-06-05T19:00:00.000Z","timestamp":"2022-06-05T19:00:00.000Z","summary":"Geekay vs The Black Lotus","attendees":[],"alarms":[],"categories":[]},{"id":634210,"uid":634210,"sequence":1,"start":"2022-06-05T20:00:00.000Z","end":"2022-06-05T21:00:00.000Z","timezone":"UTC","stamp":"2022-06-05T20:00:00.000Z","timestamp":"2022-06-05T20:00:00.000Z","summary":"RA'AD vs Anubis Gaming","attendees":[],"alarms":[],"categories":[]}]}