{"domain":"zlypher.github.io","prodId":"//Zlypher//LOL Events//EN","name":"EMEA Masters","timezone":"UTC","events":[{"id":825095,"uid":825095,"sequence":2,"start":"2023-08-15T15:00:00.000Z","end":"2023-08-15T16:00:00.000Z","timezone":"UTC","stamp":"2023-08-15T15:00:00.000Z","timestamp":"2023-08-15T15:00:00.000Z","summary":"GO vs DIA","attendees":[],"alarms":[],"categories":[]},{"id":825083,"uid":825083,"sequence":2,"start":"2023-08-15T15:00:00.000Z","end":"2023-08-15T16:00:00.000Z","timezone":"UTC","stamp":"2023-08-15T15:00:00.000Z","timestamp":"2023-08-15T15:00:00.000Z","summary":"FUT vs 7AM","attendees":[],"alarms":[],"categories":[]},{"id":825071,"uid":825071,"sequence":2,"start":"2023-08-15T15:00:00.000Z","end":"2023-08-15T16:00:00.000Z","timezone":"UTC","stamp":"2023-08-15T15:00:00.000Z","timestamp":"2023-08-15T15:00:00.000Z","summary":"DSYR vs ANO","attendees":[],"alarms":[],"categories":[]},{"id":825059,"uid":825059,"sequence":2,"start":"2023-08-15T15:00:00.000Z","end":"2023-08-15T16:00:00.000Z","timezone":"UTC","stamp":"2023-08-15T15:00:00.000Z","timestamp":"2023-08-15T15:00:00.000Z","summary":"NRD vs GTZ","attendees":[],"alarms":[],"categories":[]},{"id":825096,"uid":825096,"sequence":2,"start":"2023-08-15T16:00:00.000Z","end":"2023-08-15T17:00:00.000Z","timezone":"UTC","stamp":"2023-08-15T16:00:00.000Z","timestamp":"2023-08-15T16:00:00.000Z","summary":"ANB vs BRT","attendees":[],"alarms":[],"categories":[]},{"id":825084,"uid":825084,"sequence":2,"start":"2023-08-15T16:00:00.000Z","end":"2023-08-15T17:00:00.000Z","timezone":"UTC","stamp":"2023-08-15T16:00:00.000Z","timestamp":"2023-08-15T16:00:00.000Z","summary":"EIQ vs WD","attendees":[],"alarms":[],"categories":[]},{"id":825072,"uid":825072,"sequence":2,"start":"2023-08-15T16:00:00.000Z","end":"2023-08-15T17:00:00.000Z","timezone":"UTC","stamp":"2023-08-15T16:00:00.000Z","timestamp":"2023-08-15T16:00:00.000Z","summary":"PAR vs NGX","attendees":[],"alarms":[],"categories":[]},{"id":825060,"uid":825060,"sequence":2,"start":"2023-08-15T16:00:00.000Z","end":"2023-08-15T17:00:00.000Z","timezone":"UTC","stamp":"2023-08-15T16:00:00.000Z","timestamp":"2023-08-15T16:00:00.000Z","summary":"WLG vs GENK","attendees":[],"alarms":[],"categories":[]},{"id":825097,"uid":825097,"sequence":2,"start":"2023-08-15T17:00:00.000Z","end":"2023-08-15T18:00:00.000Z","timezone":"UTC","stamp":"2023-08-15T17:00:00.000Z","timestamp":"2023-08-15T17:00:00.000Z","summary":"ANB vs GO","attendees":[],"alarms":[],"categories":[]},{"id":825085,"uid":825085,"sequence":2,"start":"2023-08-15T17:00:00.000Z","end":"2023-08-15T18:00:00.000Z","timezone":"UTC","stamp":"2023-08-15T17:00:00.000Z","timestamp":"2023-08-15T17:00:00.000Z","summary":"7AM vs EIQ","attendees":[],"alarms":[],"categories":[]},{"id":825073,"uid":825073,"sequence":2,"start":"2023-08-15T17:00:00.000Z","end":"2023-08-15T18:00:00.000Z","timezone":"UTC","stamp":"2023-08-15T17:00:00.000Z","timestamp":"2023-08-15T17:00:00.000Z","summary":"PAR vs DSYR","attendees":[],"alarms":[],"categories":[]},{"id":825061,"uid":825061,"sequence":2,"start":"2023-08-15T17:00:00.000Z","end":"2023-08-15T18:00:00.000Z","timezone":"UTC","stamp":"2023-08-15T17:00:00.000Z","timestamp":"2023-08-15T17:00:00.000Z","summary":"GTZ vs WLG","attendees":[],"alarms":[],"categories":[]},{"id":825098,"uid":825098,"sequence":2,"start":"2023-08-15T18:00:00.000Z","end":"2023-08-15T19:00:00.000Z","timezone":"UTC","stamp":"2023-08-15T18:00:00.000Z","timestamp":"2023-08-15T18:00:00.000Z","summary":"BRT vs DIA","attendees":[],"alarms":[],"categories":[]},{"id":825086,"uid":825086,"sequence":2,"start":"2023-08-15T18:00:00.000Z","end":"2023-08-15T19:00:00.000Z","timezone":"UTC","stamp":"2023-08-15T18:00:00.000Z","timestamp":"2023-08-15T18:00:00.000Z","summary":"FUT vs WD","attendees":[],"alarms":[],"categories":[]},{"id":825074,"uid":825074,"sequence":2,"start":"2023-08-15T18:00:00.000Z","end":"2023-08-15T19:00:00.000Z","timezone":"UTC","stamp":"2023-08-15T18:00:00.000Z","timestamp":"2023-08-15T18:00:00.000Z","summary":"NGX vs ANO","attendees":[],"alarms":[],"categories":[]},{"id":825062,"uid":825062,"sequence":2,"start":"2023-08-15T18:00:00.000Z","end":"2023-08-15T19:00:00.000Z","timezone":"UTC","stamp":"2023-08-15T18:00:00.000Z","timestamp":"2023-08-15T18:00:00.000Z","summary":"GENK vs NRD","attendees":[],"alarms":[],"categories":[]},{"id":825099,"uid":825099,"sequence":2,"start":"2023-08-15T19:00:00.000Z","end":"2023-08-15T20:00:00.000Z","timezone":"UTC","stamp":"2023-08-15T19:00:00.000Z","timestamp":"2023-08-15T19:00:00.000Z","summary":"GO vs BRT","attendees":[],"alarms":[],"categories":[]},{"id":825087,"uid":825087,"sequence":2,"start":"2023-08-15T19:00:00.000Z","end":"2023-08-15T20:00:00.000Z","timezone":"UTC","stamp":"2023-08-15T19:00:00.000Z","timestamp":"2023-08-15T19:00:00.000Z","summary":"WD vs 7AM","attendees":[],"alarms":[],"categories":[]},{"id":825075,"uid":825075,"sequence":2,"start":"2023-08-15T19:00:00.000Z","end":"2023-08-15T20:00:00.000Z","timezone":"UTC","stamp":"2023-08-15T19:00:00.000Z","timestamp":"2023-08-15T19:00:00.000Z","summary":"DSYR vs NGX","attendees":[],"alarms":[],"categories":[]},{"id":825063,"uid":825063,"sequence":2,"start":"2023-08-15T19:00:00.000Z","end":"2023-08-15T20:00:00.000Z","timezone":"UTC","stamp":"2023-08-15T19:00:00.000Z","timestamp":"2023-08-15T19:00:00.000Z","summary":"NRD vs WLG","attendees":[],"alarms":[],"categories":[]},{"id":825100,"uid":825100,"sequence":2,"start":"2023-08-15T20:00:00.000Z","end":"2023-08-15T21:00:00.000Z","timezone":"UTC","stamp":"2023-08-15T20:00:00.000Z","timestamp":"2023-08-15T20:00:00.000Z","summary":"DIA vs ANB","attendees":[],"alarms":[],"categories":[]},{"id":825088,"uid":825088,"sequence":2,"start":"2023-08-15T20:00:00.000Z","end":"2023-08-15T21:00:00.000Z","timezone":"UTC","stamp":"2023-08-15T20:00:00.000Z","timestamp":"2023-08-15T20:00:00.000Z","summary":"EIQ vs FUT","attendees":[],"alarms":[],"categories":[]},{"id":825076,"uid":825076,"sequence":2,"start":"2023-08-15T20:00:00.000Z","end":"2023-08-15T21:00:00.000Z","timezone":"UTC","stamp":"2023-08-15T20:00:00.000Z","timestamp":"2023-08-15T20:00:00.000Z","summary":"ANO vs PAR","attendees":[],"alarms":[],"categories":[]},{"id":825064,"uid":825064,"sequence":2,"start":"2023-08-15T20:00:00.000Z","end":"2023-08-15T21:00:00.000Z","timezone":"UTC","stamp":"2023-08-15T20:00:00.000Z","timestamp":"2023-08-15T20:00:00.000Z","summary":"GENK vs GTZ","attendees":[],"alarms":[],"categories":[]},{"id":825102,"uid":825102,"sequence":1,"start":"2023-08-17T15:00:00.000Z","end":"2023-08-17T18:00:00.000Z","timezone":"UTC","stamp":"2023-08-17T15:00:00.000Z","timestamp":"2023-08-17T15:00:00.000Z","summary":"TBD vs TBD","attendees":[],"alarms":[],"categories":[]},{"id":825101,"uid":825101,"sequence":1,"start":"2023-08-17T15:00:00.000Z","end":"2023-08-17T18:00:00.000Z","timezone":"UTC","stamp":"2023-08-17T15:00:00.000Z","timestamp":"2023-08-17T15:00:00.000Z","summary":"TBD vs TBD","attendees":[],"alarms":[],"categories":[]},{"id":825104,"uid":825104,"sequence":1,"start":"2023-08-17T18:00:00.000Z","end":"2023-08-17T21:00:00.000Z","timezone":"UTC","stamp":"2023-08-17T18:00:00.000Z","timestamp":"2023-08-17T18:00:00.000Z","summary":"TBD vs TBD","attendees":[],"alarms":[],"categories":[]},{"id":825103,"uid":825103,"sequence":1,"start":"2023-08-17T18:00:00.000Z","end":"2023-08-17T21:00:00.000Z","timezone":"UTC","stamp":"2023-08-17T18:00:00.000Z","timestamp":"2023-08-17T18:00:00.000Z","summary":"TBD vs TBD","attendees":[],"alarms":[],"categories":[]}]}