{"domain":"zlypher.github.io","prodId":"//Zlypher//LOL Events//EN","name":"All-Star","timezone":"UTC","events":[{"id":686720,"uid":686720,"sequence":1,"start":"2022-12-11T08:00:00.000Z","end":"2022-12-11T10:00:00.000Z","timezone":"UTC","stamp":"2022-12-11T08:00:00.000Z","timestamp":"2022-12-11T08:00:00.000Z","summary":"Team 369 vs Team Crisp","attendees":[],"alarms":[],"categories":[]},{"id":686721,"uid":686721,"sequence":1,"start":"2022-12-11T10:00:00.000Z","end":"2022-12-11T12:00:00.000Z","timezone":"UTC","stamp":"2022-12-11T10:00:00.000Z","timestamp":"2022-12-11T10:00:00.000Z","summary":"Legend LPL vs Legend LCC","attendees":[],"alarms":[],"categories":[]},{"id":686722,"uid":686722,"sequence":1,"start":"2022-12-11T12:00:00.000Z","end":"2022-12-11T15:00:00.000Z","timezone":"UTC","stamp":"2022-12-11T12:00:00.000Z","timestamp":"2022-12-11T12:00:00.000Z","summary":"Team Rookie vs Team Wei","attendees":[],"alarms":[],"categories":[]}]}