{"domain":"zlypher.github.io","prodId":"//Zlypher//LOL Events//EN","name":"LFL Division 2","timezone":"UTC","events":[{"id":781138,"uid":781138,"sequence":1,"start":"2023-05-26T16:00:00.000Z","end":"2023-05-26T17:00:00.000Z","timezone":"UTC","stamp":"2023-05-26T16:00:00.000Z","timestamp":"2023-05-26T16:00:00.000Z","summary":"TDS vs MS","attendees":[],"alarms":[],"categories":[]},{"id":781139,"uid":781139,"sequence":1,"start":"2023-05-26T17:00:00.000Z","end":"2023-05-26T18:00:00.000Z","timezone":"UTC","stamp":"2023-05-26T17:00:00.000Z","timestamp":"2023-05-26T17:00:00.000Z","summary":"PCS vs LIL","attendees":[],"alarms":[],"categories":[]},{"id":781140,"uid":781140,"sequence":1,"start":"2023-05-26T18:00:00.000Z","end":"2023-05-26T19:00:00.000Z","timezone":"UTC","stamp":"2023-05-26T18:00:00.000Z","timestamp":"2023-05-26T18:00:00.000Z","summary":"VIV vs ATL","attendees":[],"alarms":[],"categories":[]},{"id":781141,"uid":781141,"sequence":1,"start":"2023-05-26T19:00:00.000Z","end":"2023-05-26T20:00:00.000Z","timezone":"UTC","stamp":"2023-05-26T19:00:00.000Z","timestamp":"2023-05-26T19:00:00.000Z","summary":"JL vs KE","attendees":[],"alarms":[],"categories":[]},{"id":781142,"uid":781142,"sequence":1,"start":"2023-05-26T20:00:00.000Z","end":"2023-05-26T21:00:00.000Z","timezone":"UTC","stamp":"2023-05-26T20:00:00.000Z","timestamp":"2023-05-26T20:00:00.000Z","summary":"MHSC Esport vs AKR","attendees":[],"alarms":[],"categories":[]}]}