{"domain":"zlypher.github.io","prodId":"//Zlypher//LOL Events//EN","name":"Iberian Cup","timezone":"UTC","events":[{"id":659760,"uid":659760,"sequence":1,"start":"2022-10-25T16:00:00.000Z","end":"2022-10-25T19:00:00.000Z","timezone":"UTC","stamp":"2022-10-25T16:00:00.000Z","timestamp":"2022-10-25T16:00:00.000Z","summary":"Round 1 match 6: CASE vs RBT","attendees":[],"alarms":[],"categories":[]},{"id":659765,"uid":659765,"sequence":1,"start":"2022-10-25T19:00:00.000Z","end":"2022-10-25T22:00:00.000Z","timezone":"UTC","stamp":"2022-10-25T19:00:00.000Z","timestamp":"2022-10-25T19:00:00.000Z","summary":"Round 1 match 9: GIA vs PAWN","attendees":[],"alarms":[],"categories":[]},{"id":659773,"uid":659773,"sequence":1,"start":"2022-10-26T16:00:00.000Z","end":"2022-10-26T19:00:00.000Z","timezone":"UTC","stamp":"2022-10-26T16:00:00.000Z","timestamp":"2022-10-26T16:00:00.000Z","summary":"Round 1 match 16: TH vs CUTE","attendees":[],"alarms":[],"categories":[]},{"id":659769,"uid":659769,"sequence":1,"start":"2022-10-26T19:00:00.000Z","end":"2022-10-26T22:00:00.000Z","timezone":"UTC","stamp":"2022-10-26T19:00:00.000Z","timestamp":"2022-10-26T19:00:00.000Z","summary":"Round 1 match 13: G2A vs PHX","attendees":[],"alarms":[],"categories":[]},{"id":659761,"uid":659761,"sequence":1,"start":"2022-10-27T16:00:00.000Z","end":"2022-10-27T19:00:00.000Z","timezone":"UTC","stamp":"2022-10-27T16:00:00.000Z","timestamp":"2022-10-27T16:00:00.000Z","summary":"Round 1 match 7: RBLS vs TDC","attendees":[],"alarms":[],"categories":[]},{"id":659768,"uid":659768,"sequence":1,"start":"2022-10-27T19:00:00.000Z","end":"2022-10-27T22:00:00.000Z","timezone":"UTC","stamp":"2022-10-27T19:00:00.000Z","timestamp":"2022-10-27T19:00:00.000Z","summary":"Round 1 match 12: BAR vs CORP","attendees":[],"alarms":[],"categories":[]},{"id":659758,"uid":659758,"sequence":1,"start":"2022-10-28T16:00:00.000Z","end":"2022-10-28T19:00:00.000Z","timezone":"UTC","stamp":"2022-10-28T16:00:00.000Z","timestamp":"2022-10-28T16:00:00.000Z","summary":"Round 1 match 4: MRS vs SB","attendees":[],"alarms":[],"categories":[]},{"id":659772,"uid":659772,"sequence":1,"start":"2022-10-28T19:00:00.000Z","end":"2022-10-28T22:00:00.000Z","timezone":"UTC","stamp":"2022-10-28T19:00:00.000Z","timestamp":"2022-10-28T19:00:00.000Z","summary":"Round 1 match 15: FAL vs ZTA","attendees":[],"alarms":[],"categories":[]},{"id":659774,"uid":659774,"sequence":1,"start":"2022-10-31T17:00:00.000Z","end":"2022-10-31T20:00:00.000Z","timezone":"UTC","stamp":"2022-10-31T17:00:00.000Z","timestamp":"2022-10-31T17:00:00.000Z","summary":"Round 2 match 1: BTS vs BSO","attendees":[],"alarms":[],"categories":[]},{"id":659775,"uid":659775,"sequence":1,"start":"2022-10-31T20:00:00.000Z","end":"2022-10-31T23:00:00.000Z","timezone":"UTC","stamp":"2022-10-31T20:00:00.000Z","timestamp":"2022-10-31T20:00:00.000Z","summary":"Round 2 match 2: UCAM vs TBD","attendees":[],"alarms":[],"categories":[]},{"id":659776,"uid":659776,"sequence":1,"start":"2022-11-01T17:00:00.000Z","end":"2022-11-01T20:00:00.000Z","timezone":"UTC","stamp":"2022-11-01T17:00:00.000Z","timestamp":"2022-11-01T17:00:00.000Z","summary":"Round 2 match 3: KOI vs TBD","attendees":[],"alarms":[],"categories":[]},{"id":659779,"uid":659779,"sequence":2,"start":"2022-11-01T20:00:00.000Z","end":"2022-11-01T23:00:00.000Z","timezone":"UTC","stamp":"2022-11-01T20:00:00.000Z","timestamp":"2022-11-01T20:00:00.000Z","summary":"Round 2 match 4: FNTQ vs TBD","attendees":[],"alarms":[],"categories":[]},{"id":659781,"uid":659781,"sequence":1,"start":"2022-11-02T17:00:00.000Z","end":"2022-11-02T20:00:00.000Z","timezone":"UTC","stamp":"2022-11-02T17:00:00.000Z","timestamp":"2022-11-02T17:00:00.000Z","summary":"Round 2 match 5: WIZ vs TBD","attendees":[],"alarms":[],"categories":[]},{"id":659783,"uid":659783,"sequence":2,"start":"2022-11-02T20:00:00.000Z","end":"2022-11-02T23:00:00.000Z","timezone":"UTC","stamp":"2022-11-02T20:00:00.000Z","timestamp":"2022-11-02T20:00:00.000Z","summary":"Round 2 match 6: GSNS vs TBD","attendees":[],"alarms":[],"categories":[]},{"id":659784,"uid":659784,"sequence":1,"start":"2022-11-03T17:00:00.000Z","end":"2022-11-03T20:00:00.000Z","timezone":"UTC","stamp":"2022-11-03T17:00:00.000Z","timestamp":"2022-11-03T17:00:00.000Z","summary":"Round 2 match 7: MADM vs TBD","attendees":[],"alarms":[],"categories":[]},{"id":659785,"uid":659785,"sequence":1,"start":"2022-11-03T20:00:00.000Z","end":"2022-11-03T23:00:00.000Z","timezone":"UTC","stamp":"2022-11-03T20:00:00.000Z","timestamp":"2022-11-03T20:00:00.000Z","summary":"Round 2 match 8: TBD vs TBD","attendees":[],"alarms":[],"categories":[]},{"id":659787,"uid":659787,"sequence":1,"start":"2022-11-07T17:00:00.000Z","end":"2022-11-07T20:00:00.000Z","timezone":"UTC","stamp":"2022-11-07T17:00:00.000Z","timestamp":"2022-11-07T17:00:00.000Z","summary":"Quarterfinal 1: TBD vs TBD","attendees":[],"alarms":[],"categories":[]},{"id":659788,"uid":659788,"sequence":1,"start":"2022-11-07T20:00:00.000Z","end":"2022-11-07T23:00:00.000Z","timezone":"UTC","stamp":"2022-11-07T20:00:00.000Z","timestamp":"2022-11-07T20:00:00.000Z","summary":"Quarterfinal 2: TBD vs TBD","attendees":[],"alarms":[],"categories":[]},{"id":659789,"uid":659789,"sequence":1,"start":"2022-11-08T17:00:00.000Z","end":"2022-11-08T20:00:00.000Z","timezone":"UTC","stamp":"2022-11-08T17:00:00.000Z","timestamp":"2022-11-08T17:00:00.000Z","summary":"Quarterfinal 3: TBD vs TBD","attendees":[],"alarms":[],"categories":[]},{"id":659791,"uid":659791,"sequence":1,"start":"2022-11-08T20:00:00.000Z","end":"2022-11-08T23:00:00.000Z","timezone":"UTC","stamp":"2022-11-08T20:00:00.000Z","timestamp":"2022-11-08T20:00:00.000Z","summary":"Quarterfinal 4: TBD vs TBD","attendees":[],"alarms":[],"categories":[]},{"id":659792,"uid":659792,"sequence":1,"start":"2022-11-14T17:00:00.000Z","end":"2022-11-14T22:00:00.000Z","timezone":"UTC","stamp":"2022-11-14T17:00:00.000Z","timestamp":"2022-11-14T17:00:00.000Z","summary":"Semifinal 1: TBD vs TBD","attendees":[],"alarms":[],"categories":[]},{"id":659793,"uid":659793,"sequence":1,"start":"2022-11-15T17:00:00.000Z","end":"2022-11-15T22:00:00.000Z","timezone":"UTC","stamp":"2022-11-15T17:00:00.000Z","timestamp":"2022-11-15T17:00:00.000Z","summary":"Semifinal 2: TBD vs TBD","attendees":[],"alarms":[],"categories":[]},{"id":659794,"uid":659794,"sequence":1,"start":"2022-11-19T17:00:00.000Z","end":"2022-11-19T22:00:00.000Z","timezone":"UTC","stamp":"2022-11-19T17:00:00.000Z","timestamp":"2022-11-19T17:00:00.000Z","summary":"Grand final: TBD vs TBD","attendees":[],"alarms":[],"categories":[]}]}