{"domain":"zlypher.github.io","prodId":"//Zlypher//LOL Events//EN","name":"LFL Division 2","timezone":"UTC","events":[{"id":813754,"uid":813754,"sequence":1,"start":"2023-08-07T16:00:00.000Z","end":"2023-08-07T21:00:00.000Z","timezone":"UTC","stamp":"2023-08-07T16:00:00.000Z","timestamp":"2023-08-07T16:00:00.000Z","summary":"Round 2 match 1: TDS vs LIL","attendees":[],"alarms":[],"categories":[]},{"id":813755,"uid":813755,"sequence":3,"start":"2023-08-08T16:00:00.000Z","end":"2023-08-08T21:00:00.000Z","timezone":"UTC","stamp":"2023-08-08T16:00:00.000Z","timestamp":"2023-08-08T16:00:00.000Z","summary":"Round 2 match 2: ATL vs PCS","attendees":[],"alarms":[],"categories":[]},{"id":813757,"uid":813757,"sequence":1,"start":"2023-08-12T16:00:00.000Z","end":"2023-08-12T21:00:00.000Z","timezone":"UTC","stamp":"2023-08-12T16:00:00.000Z","timestamp":"2023-08-12T16:00:00.000Z","summary":"Semifinal: TBD vs TBD","attendees":[],"alarms":[],"categories":[]},{"id":813758,"uid":813758,"sequence":1,"start":"2023-08-13T16:00:00.000Z","end":"2023-08-13T21:00:00.000Z","timezone":"UTC","stamp":"2023-08-13T16:00:00.000Z","timestamp":"2023-08-13T16:00:00.000Z","summary":"Grand final: TBD vs TBD","attendees":[],"alarms":[],"categories":[]}]}