{"domain":"zlypher.github.io","prodId":"//Zlypher//LOL Events//EN","name":"PG Nationals","timezone":"UTC","events":[{"id":581081,"uid":581081,"sequence":1,"start":"2021-01-20T18:00:00.000Z","end":"2021-01-20T19:00:00.000Z","timezone":"UTC","stamp":"2021-01-20T18:00:00.000Z","timestamp":"2021-01-20T18:00:00.000Z","summary":"OP vs RML","attendees":[],"alarms":[],"categories":[]},{"id":581082,"uid":581082,"sequence":1,"start":"2021-01-20T19:00:00.000Z","end":"2021-01-20T20:00:00.000Z","timezone":"UTC","stamp":"2021-01-20T19:00:00.000Z","timestamp":"2021-01-20T19:00:00.000Z","summary":"MKS vs SMS","attendees":[],"alarms":[],"categories":[]},{"id":581083,"uid":581083,"sequence":1,"start":"2021-01-20T20:00:00.000Z","end":"2021-01-20T21:00:00.000Z","timezone":"UTC","stamp":"2021-01-20T20:00:00.000Z","timestamp":"2021-01-20T20:00:00.000Z","summary":"GGE vs MCK","attendees":[],"alarms":[],"categories":[]},{"id":581084,"uid":581084,"sequence":1,"start":"2021-01-20T21:00:00.000Z","end":"2021-01-20T22:00:00.000Z","timezone":"UTC","stamp":"2021-01-20T21:00:00.000Z","timestamp":"2021-01-20T21:00:00.000Z","summary":"CGG vs AXL","attendees":[],"alarms":[],"categories":[]},{"id":581085,"uid":581085,"sequence":1,"start":"2021-01-21T18:00:00.000Z","end":"2021-01-21T19:00:00.000Z","timezone":"UTC","stamp":"2021-01-21T18:00:00.000Z","timestamp":"2021-01-21T18:00:00.000Z","summary":"MCK vs MKS","attendees":[],"alarms":[],"categories":[]},{"id":581086,"uid":581086,"sequence":1,"start":"2021-01-21T19:00:00.000Z","end":"2021-01-21T20:00:00.000Z","timezone":"UTC","stamp":"2021-01-21T19:00:00.000Z","timestamp":"2021-01-21T19:00:00.000Z","summary":"RML vs CGG","attendees":[],"alarms":[],"categories":[]},{"id":581087,"uid":581087,"sequence":1,"start":"2021-01-21T20:00:00.000Z","end":"2021-01-21T21:00:00.000Z","timezone":"UTC","stamp":"2021-01-21T20:00:00.000Z","timestamp":"2021-01-21T20:00:00.000Z","summary":"SMS vs OP","attendees":[],"alarms":[],"categories":[]},{"id":581088,"uid":581088,"sequence":1,"start":"2021-01-21T21:00:00.000Z","end":"2021-01-21T22:00:00.000Z","timezone":"UTC","stamp":"2021-01-21T21:00:00.000Z","timestamp":"2021-01-21T21:00:00.000Z","summary":"AXL vs GGE","attendees":[],"alarms":[],"categories":[]},{"id":581089,"uid":581089,"sequence":1,"start":"2021-01-27T18:00:00.000Z","end":"2021-01-27T19:00:00.000Z","timezone":"UTC","stamp":"2021-01-27T18:00:00.000Z","timestamp":"2021-01-27T18:00:00.000Z","summary":"AXL vs RML","attendees":[],"alarms":[],"categories":[]},{"id":581090,"uid":581090,"sequence":1,"start":"2021-01-27T19:00:00.000Z","end":"2021-01-27T20:00:00.000Z","timezone":"UTC","stamp":"2021-01-27T19:00:00.000Z","timestamp":"2021-01-27T19:00:00.000Z","summary":"OP vs MCK","attendees":[],"alarms":[],"categories":[]},{"id":581091,"uid":581091,"sequence":1,"start":"2021-01-27T20:00:00.000Z","end":"2021-01-27T21:00:00.000Z","timezone":"UTC","stamp":"2021-01-27T20:00:00.000Z","timestamp":"2021-01-27T20:00:00.000Z","summary":"CGG vs SMS","attendees":[],"alarms":[],"categories":[]},{"id":581092,"uid":581092,"sequence":1,"start":"2021-01-27T21:00:00.000Z","end":"2021-01-27T22:00:00.000Z","timezone":"UTC","stamp":"2021-01-27T21:00:00.000Z","timestamp":"2021-01-27T21:00:00.000Z","summary":"GGE vs MKS","attendees":[],"alarms":[],"categories":[]},{"id":581093,"uid":581093,"sequence":1,"start":"2021-01-28T18:00:00.000Z","end":"2021-01-28T19:00:00.000Z","timezone":"UTC","stamp":"2021-01-28T18:00:00.000Z","timestamp":"2021-01-28T18:00:00.000Z","summary":"MCK vs CGG","attendees":[],"alarms":[],"categories":[]},{"id":581094,"uid":581094,"sequence":1,"start":"2021-01-28T19:00:00.000Z","end":"2021-01-28T20:00:00.000Z","timezone":"UTC","stamp":"2021-01-28T19:00:00.000Z","timestamp":"2021-01-28T19:00:00.000Z","summary":"SMS vs AXL","attendees":[],"alarms":[],"categories":[]},{"id":581095,"uid":581095,"sequence":1,"start":"2021-01-28T20:00:00.000Z","end":"2021-01-28T21:00:00.000Z","timezone":"UTC","stamp":"2021-01-28T20:00:00.000Z","timestamp":"2021-01-28T20:00:00.000Z","summary":"RML vs GGE","attendees":[],"alarms":[],"categories":[]},{"id":581096,"uid":581096,"sequence":1,"start":"2021-01-28T21:00:00.000Z","end":"2021-01-28T22:00:00.000Z","timezone":"UTC","stamp":"2021-01-28T21:00:00.000Z","timestamp":"2021-01-28T21:00:00.000Z","summary":"MKS vs OP","attendees":[],"alarms":[],"categories":[]},{"id":581097,"uid":581097,"sequence":1,"start":"2021-02-03T18:00:00.000Z","end":"2021-02-03T19:00:00.000Z","timezone":"UTC","stamp":"2021-02-03T18:00:00.000Z","timestamp":"2021-02-03T18:00:00.000Z","summary":"CGG vs MKS","attendees":[],"alarms":[],"categories":[]},{"id":581098,"uid":581098,"sequence":1,"start":"2021-02-03T19:00:00.000Z","end":"2021-02-03T20:00:00.000Z","timezone":"UTC","stamp":"2021-02-03T19:00:00.000Z","timestamp":"2021-02-03T19:00:00.000Z","summary":"GGE vs OP","attendees":[],"alarms":[],"categories":[]},{"id":581099,"uid":581099,"sequence":1,"start":"2021-02-03T20:00:00.000Z","end":"2021-02-03T21:00:00.000Z","timezone":"UTC","stamp":"2021-02-03T20:00:00.000Z","timestamp":"2021-02-03T20:00:00.000Z","summary":"AXL vs MCK","attendees":[],"alarms":[],"categories":[]},{"id":581100,"uid":581100,"sequence":1,"start":"2021-02-03T21:00:00.000Z","end":"2021-02-03T22:00:00.000Z","timezone":"UTC","stamp":"2021-02-03T21:00:00.000Z","timestamp":"2021-02-03T21:00:00.000Z","summary":"RML vs SMS","attendees":[],"alarms":[],"categories":[]},{"id":581101,"uid":581101,"sequence":1,"start":"2021-02-04T18:00:00.000Z","end":"2021-02-04T19:00:00.000Z","timezone":"UTC","stamp":"2021-02-04T18:00:00.000Z","timestamp":"2021-02-04T18:00:00.000Z","summary":"SMS vs GGE","attendees":[],"alarms":[],"categories":[]},{"id":581102,"uid":581102,"sequence":1,"start":"2021-02-04T19:00:00.000Z","end":"2021-02-04T20:00:00.000Z","timezone":"UTC","stamp":"2021-02-04T19:00:00.000Z","timestamp":"2021-02-04T19:00:00.000Z","summary":"RML vs MCK","attendees":[],"alarms":[],"categories":[]},{"id":581103,"uid":581103,"sequence":1,"start":"2021-02-04T20:00:00.000Z","end":"2021-02-04T21:00:00.000Z","timezone":"UTC","stamp":"2021-02-04T20:00:00.000Z","timestamp":"2021-02-04T20:00:00.000Z","summary":"AXL vs MKS","attendees":[],"alarms":[],"categories":[]},{"id":581104,"uid":581104,"sequence":1,"start":"2021-02-04T21:00:00.000Z","end":"2021-02-04T22:00:00.000Z","timezone":"UTC","stamp":"2021-02-04T21:00:00.000Z","timestamp":"2021-02-04T21:00:00.000Z","summary":"CGG vs OP","attendees":[],"alarms":[],"categories":[]},{"id":581105,"uid":581105,"sequence":1,"start":"2021-02-10T18:00:00.000Z","end":"2021-02-10T19:00:00.000Z","timezone":"UTC","stamp":"2021-02-10T18:00:00.000Z","timestamp":"2021-02-10T18:00:00.000Z","summary":"OP vs AXL","attendees":[],"alarms":[],"categories":[]},{"id":581106,"uid":581106,"sequence":1,"start":"2021-02-10T19:00:00.000Z","end":"2021-02-10T20:00:00.000Z","timezone":"UTC","stamp":"2021-02-10T19:00:00.000Z","timestamp":"2021-02-10T19:00:00.000Z","summary":"GGE vs CGG","attendees":[],"alarms":[],"categories":[]},{"id":581107,"uid":581107,"sequence":1,"start":"2021-02-10T20:00:00.000Z","end":"2021-02-10T21:00:00.000Z","timezone":"UTC","stamp":"2021-02-10T20:00:00.000Z","timestamp":"2021-02-10T20:00:00.000Z","summary":"MKS vs RML","attendees":[],"alarms":[],"categories":[]},{"id":581108,"uid":581108,"sequence":1,"start":"2021-02-10T21:00:00.000Z","end":"2021-02-10T22:00:00.000Z","timezone":"UTC","stamp":"2021-02-10T21:00:00.000Z","timestamp":"2021-02-10T21:00:00.000Z","summary":"MCK vs SMS","attendees":[],"alarms":[],"categories":[]},{"id":581109,"uid":581109,"sequence":1,"start":"2021-02-11T18:00:00.000Z","end":"2021-02-11T19:00:00.000Z","timezone":"UTC","stamp":"2021-02-11T18:00:00.000Z","timestamp":"2021-02-11T18:00:00.000Z","summary":"RML vs OP","attendees":[],"alarms":[],"categories":[]},{"id":581110,"uid":581110,"sequence":1,"start":"2021-02-11T19:00:00.000Z","end":"2021-02-11T20:00:00.000Z","timezone":"UTC","stamp":"2021-02-11T19:00:00.000Z","timestamp":"2021-02-11T19:00:00.000Z","summary":"SMS vs MKS","attendees":[],"alarms":[],"categories":[]},{"id":581111,"uid":581111,"sequence":1,"start":"2021-02-11T20:00:00.000Z","end":"2021-02-11T21:00:00.000Z","timezone":"UTC","stamp":"2021-02-11T20:00:00.000Z","timestamp":"2021-02-11T20:00:00.000Z","summary":"MCK vs GGE","attendees":[],"alarms":[],"categories":[]},{"id":581112,"uid":581112,"sequence":1,"start":"2021-02-11T21:00:00.000Z","end":"2021-02-11T22:00:00.000Z","timezone":"UTC","stamp":"2021-02-11T21:00:00.000Z","timestamp":"2021-02-11T21:00:00.000Z","summary":"AXL vs CGG","attendees":[],"alarms":[],"categories":[]},{"id":581113,"uid":581113,"sequence":1,"start":"2021-02-17T18:00:00.000Z","end":"2021-02-17T19:00:00.000Z","timezone":"UTC","stamp":"2021-02-17T18:00:00.000Z","timestamp":"2021-02-17T18:00:00.000Z","summary":"MKS vs MCK","attendees":[],"alarms":[],"categories":[]},{"id":581114,"uid":581114,"sequence":1,"start":"2021-02-17T19:00:00.000Z","end":"2021-02-17T20:00:00.000Z","timezone":"UTC","stamp":"2021-02-17T19:00:00.000Z","timestamp":"2021-02-17T19:00:00.000Z","summary":"CGG vs RML","attendees":[],"alarms":[],"categories":[]},{"id":581115,"uid":581115,"sequence":1,"start":"2021-02-17T20:00:00.000Z","end":"2021-02-17T21:00:00.000Z","timezone":"UTC","stamp":"2021-02-17T20:00:00.000Z","timestamp":"2021-02-17T20:00:00.000Z","summary":"OP vs SMS","attendees":[],"alarms":[],"categories":[]},{"id":581116,"uid":581116,"sequence":1,"start":"2021-02-17T21:00:00.000Z","end":"2021-02-17T22:00:00.000Z","timezone":"UTC","stamp":"2021-02-17T21:00:00.000Z","timestamp":"2021-02-17T21:00:00.000Z","summary":"GGE vs AXL","attendees":[],"alarms":[],"categories":[]},{"id":581117,"uid":581117,"sequence":1,"start":"2021-02-18T18:00:00.000Z","end":"2021-02-18T19:00:00.000Z","timezone":"UTC","stamp":"2021-02-18T18:00:00.000Z","timestamp":"2021-02-18T18:00:00.000Z","summary":"RML vs AXL","attendees":[],"alarms":[],"categories":[]},{"id":581118,"uid":581118,"sequence":1,"start":"2021-02-18T19:00:00.000Z","end":"2021-02-18T20:00:00.000Z","timezone":"UTC","stamp":"2021-02-18T19:00:00.000Z","timestamp":"2021-02-18T19:00:00.000Z","summary":"MCK vs OP","attendees":[],"alarms":[],"categories":[]},{"id":581119,"uid":581119,"sequence":1,"start":"2021-02-18T20:00:00.000Z","end":"2021-02-18T21:00:00.000Z","timezone":"UTC","stamp":"2021-02-18T20:00:00.000Z","timestamp":"2021-02-18T20:00:00.000Z","summary":"SMS vs CGG","attendees":[],"alarms":[],"categories":[]},{"id":581120,"uid":581120,"sequence":1,"start":"2021-02-18T21:00:00.000Z","end":"2021-02-18T22:00:00.000Z","timezone":"UTC","stamp":"2021-02-18T21:00:00.000Z","timestamp":"2021-02-18T21:00:00.000Z","summary":"MKS vs GGE","attendees":[],"alarms":[],"categories":[]},{"id":581121,"uid":581121,"sequence":1,"start":"2021-02-24T18:00:00.000Z","end":"2021-02-24T19:00:00.000Z","timezone":"UTC","stamp":"2021-02-24T18:00:00.000Z","timestamp":"2021-02-24T18:00:00.000Z","summary":"CGG vs MCK","attendees":[],"alarms":[],"categories":[]},{"id":581122,"uid":581122,"sequence":1,"start":"2021-02-24T19:00:00.000Z","end":"2021-02-24T20:00:00.000Z","timezone":"UTC","stamp":"2021-02-24T19:00:00.000Z","timestamp":"2021-02-24T19:00:00.000Z","summary":"AXL vs SMS","attendees":[],"alarms":[],"categories":[]},{"id":581123,"uid":581123,"sequence":1,"start":"2021-02-24T20:00:00.000Z","end":"2021-02-24T21:00:00.000Z","timezone":"UTC","stamp":"2021-02-24T20:00:00.000Z","timestamp":"2021-02-24T20:00:00.000Z","summary":"GGE vs RML","attendees":[],"alarms":[],"categories":[]},{"id":581124,"uid":581124,"sequence":1,"start":"2021-02-24T21:00:00.000Z","end":"2021-02-24T22:00:00.000Z","timezone":"UTC","stamp":"2021-02-24T21:00:00.000Z","timestamp":"2021-02-24T21:00:00.000Z","summary":"OP vs MKS","attendees":[],"alarms":[],"categories":[]},{"id":581125,"uid":581125,"sequence":1,"start":"2021-02-25T18:00:00.000Z","end":"2021-02-25T19:00:00.000Z","timezone":"UTC","stamp":"2021-02-25T18:00:00.000Z","timestamp":"2021-02-25T18:00:00.000Z","summary":"MKS vs CGG","attendees":[],"alarms":[],"categories":[]},{"id":581126,"uid":581126,"sequence":1,"start":"2021-02-25T19:00:00.000Z","end":"2021-02-25T20:00:00.000Z","timezone":"UTC","stamp":"2021-02-25T19:00:00.000Z","timestamp":"2021-02-25T19:00:00.000Z","summary":"OP vs GGE","attendees":[],"alarms":[],"categories":[]},{"id":581127,"uid":581127,"sequence":1,"start":"2021-02-25T20:00:00.000Z","end":"2021-02-25T21:00:00.000Z","timezone":"UTC","stamp":"2021-02-25T20:00:00.000Z","timestamp":"2021-02-25T20:00:00.000Z","summary":"MCK vs AXL","attendees":[],"alarms":[],"categories":[]},{"id":581128,"uid":581128,"sequence":1,"start":"2021-02-25T21:00:00.000Z","end":"2021-02-25T22:00:00.000Z","timezone":"UTC","stamp":"2021-02-25T21:00:00.000Z","timestamp":"2021-02-25T21:00:00.000Z","summary":"SMS vs RML","attendees":[],"alarms":[],"categories":[]}]}