{"domain":"zlypher.github.io","prodId":"//Zlypher//LOL Events//EN","name":"Road Of Legends","timezone":"UTC","events":[{"id":1149596,"uid":1149596,"sequence":1,"start":"2025-04-01T18:02:13.000Z","end":"2025-04-01T21:02:13.000Z","timezone":"UTC","stamp":"2025-04-01T18:02:13.000Z","timestamp":"2025-04-01T18:02:13.000Z","summary":"AOMA vs SEC","attendees":[],"alarms":[],"categories":[]},{"id":1149595,"uid":1149595,"sequence":1,"start":"2025-04-01T17:02:47.000Z","end":"2025-04-01T20:02:47.000Z","timezone":"UTC","stamp":"2025-04-01T17:02:47.000Z","timestamp":"2025-04-01T17:02:47.000Z","summary":"ZNT vs MCN","attendees":[],"alarms":[],"categories":[]},{"id":1149594,"uid":1149594,"sequence":1,"start":"2025-03-27T19:20:16.000Z","end":"2025-03-27T22:20:16.000Z","timezone":"UTC","stamp":"2025-03-27T19:20:16.000Z","timestamp":"2025-03-27T19:20:16.000Z","summary":"ZNT vs AURORA","attendees":[],"alarms":[],"categories":[]},{"id":1149593,"uid":1149593,"sequence":1,"start":"2025-03-27T18:02:31.000Z","end":"2025-03-27T21:02:31.000Z","timezone":"UTC","stamp":"2025-03-27T18:02:31.000Z","timestamp":"2025-03-27T18:02:31.000Z","summary":"AOMA vs JMGG","attendees":[],"alarms":[],"categories":[]},{"id":1149592,"uid":1149592,"sequence":1,"start":"2025-03-25T19:13:18.000Z","end":"2025-03-25T22:13:18.000Z","timezone":"UTC","stamp":"2025-03-25T19:13:18.000Z","timestamp":"2025-03-25T19:13:18.000Z","summary":"OUAT vs MCN","attendees":[],"alarms":[],"categories":[]},{"id":1149591,"uid":1149591,"sequence":1,"start":"2025-03-25T18:06:55.000Z","end":"2025-03-25T21:06:55.000Z","timezone":"UTC","stamp":"2025-03-25T18:06:55.000Z","timestamp":"2025-03-25T18:06:55.000Z","summary":"MYTH vs SEC","attendees":[],"alarms":[],"categories":[]},{"id":1121366,"uid":1121366,"sequence":1,"start":"2025-03-06T18:01:16.000Z","end":"2025-03-06T23:01:16.000Z","timezone":"UTC","stamp":"2025-03-06T18:01:16.000Z","timestamp":"2025-03-06T18:01:16.000Z","summary":"Grand final: ZNT vs MCN","attendees":[],"alarms":[],"categories":[]},{"id":1121365,"uid":1121365,"sequence":1,"start":"2025-03-04T18:01:31.000Z","end":"2025-03-04T23:01:31.000Z","timezone":"UTC","stamp":"2025-03-04T18:01:31.000Z","timestamp":"2025-03-04T18:01:31.000Z","summary":"Semifinal: AOMA vs MCN","attendees":[],"alarms":[],"categories":[]},{"id":1121364,"uid":1121364,"sequence":1,"start":"2025-02-27T18:01:14.000Z","end":"2025-02-27T23:01:14.000Z","timezone":"UTC","stamp":"2025-02-27T18:01:14.000Z","timestamp":"2025-02-27T18:01:14.000Z","summary":"Round 1 match 1: AOMA vs ZNT","attendees":[],"alarms":[],"categories":[]},{"id":1121363,"uid":1121363,"sequence":1,"start":"2025-02-25T18:00:26.000Z","end":"2025-02-25T23:00:26.000Z","timezone":"UTC","stamp":"2025-02-25T18:00:26.000Z","timestamp":"2025-02-25T18:00:26.000Z","summary":"Round 1 match 2: MCN vs MYTH","attendees":[],"alarms":[],"categories":[]},{"id":1121361,"uid":1121361,"sequence":1,"start":"2025-02-20T19:13:27.000Z","end":"2025-02-20T22:13:27.000Z","timezone":"UTC","stamp":"2025-02-20T19:13:27.000Z","timestamp":"2025-02-20T19:13:27.000Z","summary":"Round 3: MCN vs OUAT","attendees":[],"alarms":[],"categories":[]},{"id":1121362,"uid":1121362,"sequence":1,"start":"2025-02-20T18:04:29.000Z","end":"2025-02-20T21:04:29.000Z","timezone":"UTC","stamp":"2025-02-20T18:04:29.000Z","timestamp":"2025-02-20T18:04:29.000Z","summary":"Round 3: JMGG vs MYTH","attendees":[],"alarms":[],"categories":[]},{"id":1121360,"uid":1121360,"sequence":1,"start":"2025-02-19T19:05:54.000Z","end":"2025-02-19T22:05:54.000Z","timezone":"UTC","stamp":"2025-02-19T19:05:54.000Z","timestamp":"2025-02-19T19:05:54.000Z","summary":"Round 2: AURORA vs JMGG","attendees":[],"alarms":[],"categories":[]},{"id":1121359,"uid":1121359,"sequence":1,"start":"2025-02-19T18:00:22.000Z","end":"2025-02-19T21:00:22.000Z","timezone":"UTC","stamp":"2025-02-19T18:00:22.000Z","timestamp":"2025-02-19T18:00:22.000Z","summary":"Round 2: OUAT vs SEC","attendees":[],"alarms":[],"categories":[]},{"id":1121358,"uid":1121358,"sequence":1,"start":"2025-02-18T19:06:55.000Z","end":"2025-02-18T22:06:55.000Z","timezone":"UTC","stamp":"2025-02-18T19:06:55.000Z","timestamp":"2025-02-18T19:06:55.000Z","summary":"Round 2: AOMA vs MYTH","attendees":[],"alarms":[],"categories":[]},{"id":1121356,"uid":1121356,"sequence":1,"start":"2025-02-18T18:01:31.000Z","end":"2025-02-18T21:01:31.000Z","timezone":"UTC","stamp":"2025-02-18T18:01:31.000Z","timestamp":"2025-02-18T18:01:31.000Z","summary":"Round 2: ZNT vs MCN","attendees":[],"alarms":[],"categories":[]},{"id":1121355,"uid":1121355,"sequence":1,"start":"2025-02-13T19:48:32.000Z","end":"2025-02-13T22:48:32.000Z","timezone":"UTC","stamp":"2025-02-13T19:48:32.000Z","timestamp":"2025-02-13T19:48:32.000Z","summary":"Round 1: MCN vs JMGG","attendees":[],"alarms":[],"categories":[]},{"id":1121353,"uid":1121353,"sequence":1,"start":"2025-02-13T18:04:01.000Z","end":"2025-02-13T21:04:01.000Z","timezone":"UTC","stamp":"2025-02-13T18:04:01.000Z","timestamp":"2025-02-13T18:04:01.000Z","summary":"Round 1: AURORA vs MYTH","attendees":[],"alarms":[],"categories":[]},{"id":1121350,"uid":1121350,"sequence":1,"start":"2025-02-11T19:11:01.000Z","end":"2025-02-11T22:11:01.000Z","timezone":"UTC","stamp":"2025-02-11T19:11:01.000Z","timestamp":"2025-02-11T19:11:01.000Z","summary":"Round 1: ZNT vs SEC","attendees":[],"alarms":[],"categories":[]},{"id":1121349,"uid":1121349,"sequence":1,"start":"2025-02-11T18:09:26.000Z","end":"2025-02-11T21:09:26.000Z","timezone":"UTC","stamp":"2025-02-11T18:09:26.000Z","timestamp":"2025-02-11T18:09:26.000Z","summary":"Round 1: OUAT vs AOMA","attendees":[],"alarms":[],"categories":[]},{"id":1149597,"uid":1149597,"sequence":1,"start":"2025-04-03T17:00:00.000Z","end":"2025-04-03T20:00:00.000Z","timezone":"UTC","stamp":"2025-04-03T17:00:00.000Z","timestamp":"2025-04-03T17:00:00.000Z","summary":"OUAT vs AURORA","attendees":[],"alarms":[],"categories":[]},{"id":1149598,"uid":1149598,"sequence":1,"start":"2025-04-03T18:00:00.000Z","end":"2025-04-03T21:00:00.000Z","timezone":"UTC","stamp":"2025-04-03T18:00:00.000Z","timestamp":"2025-04-03T18:00:00.000Z","summary":"MYTH vs JMGG","attendees":[],"alarms":[],"categories":[]},{"id":1149599,"uid":1149599,"sequence":1,"start":"2025-04-08T17:00:00.000Z","end":"2025-04-08T20:00:00.000Z","timezone":"UTC","stamp":"2025-04-08T17:00:00.000Z","timestamp":"2025-04-08T17:00:00.000Z","summary":"MYTH vs AURORA","attendees":[],"alarms":[],"categories":[]},{"id":1149600,"uid":1149600,"sequence":1,"start":"2025-04-08T18:00:00.000Z","end":"2025-04-08T21:00:00.000Z","timezone":"UTC","stamp":"2025-04-08T18:00:00.000Z","timestamp":"2025-04-08T18:00:00.000Z","summary":"OUAT vs JMGG","attendees":[],"alarms":[],"categories":[]},{"id":1149601,"uid":1149601,"sequence":1,"start":"2025-04-10T17:00:00.000Z","end":"2025-04-10T20:00:00.000Z","timezone":"UTC","stamp":"2025-04-10T17:00:00.000Z","timestamp":"2025-04-10T17:00:00.000Z","summary":"AOMA vs MCN","attendees":[],"alarms":[],"categories":[]},{"id":1149603,"uid":1149603,"sequence":1,"start":"2025-04-10T18:00:00.000Z","end":"2025-04-10T21:00:00.000Z","timezone":"UTC","stamp":"2025-04-10T18:00:00.000Z","timestamp":"2025-04-10T18:00:00.000Z","summary":"ZNT vs SEC","attendees":[],"alarms":[],"categories":[]},{"id":1149604,"uid":1149604,"sequence":1,"start":"2025-04-15T17:00:00.000Z","end":"2025-04-15T20:00:00.000Z","timezone":"UTC","stamp":"2025-04-15T17:00:00.000Z","timestamp":"2025-04-15T17:00:00.000Z","summary":"ZNT vs JMGG","attendees":[],"alarms":[],"categories":[]},{"id":1149605,"uid":1149605,"sequence":1,"start":"2025-04-15T18:00:00.000Z","end":"2025-04-15T21:00:00.000Z","timezone":"UTC","stamp":"2025-04-15T18:00:00.000Z","timestamp":"2025-04-15T18:00:00.000Z","summary":"MYTH vs MCN","attendees":[],"alarms":[],"categories":[]},{"id":1149606,"uid":1149606,"sequence":1,"start":"2025-04-17T17:00:00.000Z","end":"2025-04-17T20:00:00.000Z","timezone":"UTC","stamp":"2025-04-17T17:00:00.000Z","timestamp":"2025-04-17T17:00:00.000Z","summary":"OUAT vs SEC","attendees":[],"alarms":[],"categories":[]},{"id":1149607,"uid":1149607,"sequence":1,"start":"2025-04-17T18:00:00.000Z","end":"2025-04-17T21:00:00.000Z","timezone":"UTC","stamp":"2025-04-17T18:00:00.000Z","timestamp":"2025-04-17T18:00:00.000Z","summary":"AOMA vs AURORA","attendees":[],"alarms":[],"categories":[]},{"id":1149608,"uid":1149608,"sequence":1,"start":"2025-04-22T17:00:00.000Z","end":"2025-04-22T20:00:00.000Z","timezone":"UTC","stamp":"2025-04-22T17:00:00.000Z","timestamp":"2025-04-22T17:00:00.000Z","summary":"ZNT vs AOMA","attendees":[],"alarms":[],"categories":[]},{"id":1149610,"uid":1149610,"sequence":1,"start":"2025-04-22T18:00:00.000Z","end":"2025-04-22T21:00:00.000Z","timezone":"UTC","stamp":"2025-04-22T18:00:00.000Z","timestamp":"2025-04-22T18:00:00.000Z","summary":"SEC vs AURORA","attendees":[],"alarms":[],"categories":[]},{"id":1149611,"uid":1149611,"sequence":1,"start":"2025-04-24T17:00:00.000Z","end":"2025-04-24T20:00:00.000Z","timezone":"UTC","stamp":"2025-04-24T17:00:00.000Z","timestamp":"2025-04-24T17:00:00.000Z","summary":"MCN vs JMGG","attendees":[],"alarms":[],"categories":[]},{"id":1149612,"uid":1149612,"sequence":1,"start":"2025-04-24T18:00:00.000Z","end":"2025-04-24T21:00:00.000Z","timezone":"UTC","stamp":"2025-04-24T18:00:00.000Z","timestamp":"2025-04-24T18:00:00.000Z","summary":"OUAT vs MYTH","attendees":[],"alarms":[],"categories":[]},{"id":1149613,"uid":1149613,"sequence":1,"start":"2025-04-29T17:00:00.000Z","end":"2025-04-29T20:00:00.000Z","timezone":"UTC","stamp":"2025-04-29T17:00:00.000Z","timestamp":"2025-04-29T17:00:00.000Z","summary":"MCN vs AURORA","attendees":[],"alarms":[],"categories":[]},{"id":1149614,"uid":1149614,"sequence":1,"start":"2025-04-29T18:00:00.000Z","end":"2025-04-29T21:00:00.000Z","timezone":"UTC","stamp":"2025-04-29T18:00:00.000Z","timestamp":"2025-04-29T18:00:00.000Z","summary":"ZNT vs OUAT","attendees":[],"alarms":[],"categories":[]},{"id":1149617,"uid":1149617,"sequence":1,"start":"2025-05-01T17:00:00.000Z","end":"2025-05-01T20:00:00.000Z","timezone":"UTC","stamp":"2025-05-01T17:00:00.000Z","timestamp":"2025-05-01T17:00:00.000Z","summary":"SEC vs JMGG","attendees":[],"alarms":[],"categories":[]},{"id":1149616,"uid":1149616,"sequence":1,"start":"2025-05-01T18:00:00.000Z","end":"2025-05-01T21:00:00.000Z","timezone":"UTC","stamp":"2025-05-01T18:00:00.000Z","timestamp":"2025-05-01T18:00:00.000Z","summary":"AOMA vs MYTH","attendees":[],"alarms":[],"categories":[]},{"id":1149618,"uid":1149618,"sequence":1,"start":"2025-05-06T17:00:00.000Z","end":"2025-05-06T20:00:00.000Z","timezone":"UTC","stamp":"2025-05-06T17:00:00.000Z","timestamp":"2025-05-06T17:00:00.000Z","summary":"OUAT vs AOMA","attendees":[],"alarms":[],"categories":[]},{"id":1149619,"uid":1149619,"sequence":1,"start":"2025-05-06T18:00:00.000Z","end":"2025-05-06T21:00:00.000Z","timezone":"UTC","stamp":"2025-05-06T18:00:00.000Z","timestamp":"2025-05-06T18:00:00.000Z","summary":"AURORA vs JMGG","attendees":[],"alarms":[],"categories":[]},{"id":1149620,"uid":1149620,"sequence":1,"start":"2025-05-08T17:00:00.000Z","end":"2025-05-08T20:00:00.000Z","timezone":"UTC","stamp":"2025-05-08T17:00:00.000Z","timestamp":"2025-05-08T17:00:00.000Z","summary":"ZNT vs MYTH","attendees":[],"alarms":[],"categories":[]},{"id":1149621,"uid":1149621,"sequence":1,"start":"2025-05-08T18:00:00.000Z","end":"2025-05-08T21:00:00.000Z","timezone":"UTC","stamp":"2025-05-08T18:00:00.000Z","timestamp":"2025-05-08T18:00:00.000Z","summary":"MCN vs SEC","attendees":[],"alarms":[],"categories":[]}]}