{"domain":"zlypher.github.io","prodId":"//Zlypher//LOL Events//EN","name":"Asia Star Challengers Invitational","timezone":"UTC","events":[{"id":1037747,"uid":1037747,"sequence":1,"start":"2024-09-10T11:35:20.000Z","end":"2024-09-10T14:35:20.000Z","timezone":"UTC","stamp":"2024-09-10T11:35:20.000Z","timestamp":"2024-09-10T11:35:20.000Z","summary":"Grand final: KDF.C vs WBG.Y","attendees":[],"alarms":[],"categories":[]},{"id":1037753,"uid":1037753,"sequence":1,"start":"2024-09-10T08:41:06.000Z","end":"2024-09-10T11:41:06.000Z","timezone":"UTC","stamp":"2024-09-10T08:41:06.000Z","timestamp":"2024-09-10T08:41:06.000Z","summary":"Grand final: CTBC.A vs DK.C","attendees":[],"alarms":[],"categories":[]},{"id":1037736,"uid":1037736,"sequence":1,"start":"2024-09-10T07:03:57.000Z","end":"2024-09-10T10:03:57.000Z","timezone":"UTC","stamp":"2024-09-10T07:03:57.000Z","timestamp":"2024-09-10T07:03:57.000Z","summary":"Grand final: T1.A vs KT.C","attendees":[],"alarms":[],"categories":[]},{"id":1037752,"uid":1037752,"sequence":1,"start":"2024-09-09T07:00:00.000Z","end":"2024-09-09T10:00:00.000Z","timezone":"UTC","stamp":"2024-09-09T07:00:00.000Z","timestamp":"2024-09-09T07:00:00.000Z","summary":"Semifinal 2: LGDY vs WBG.Y","attendees":[],"alarms":[],"categories":[]},{"id":836241,"uid":836241,"sequence":1,"start":"2023-09-15T10:07:26.000Z","end":"2023-09-15T15:07:26.000Z","timezone":"UTC","stamp":"2023-09-15T10:07:26.000Z","timestamp":"2023-09-15T10:07:26.000Z","summary":"Grand final: MAX vs DRX.C","attendees":[],"alarms":[],"categories":[]},{"id":836243,"uid":836243,"sequence":1,"start":"2023-09-14T10:06:15.000Z","end":"2023-09-14T15:06:15.000Z","timezone":"UTC","stamp":"2023-09-14T10:06:15.000Z","timestamp":"2023-09-14T10:06:15.000Z","summary":"Semifinal 2: DRX.C vs HLE","attendees":[],"alarms":[],"categories":[]},{"id":836239,"uid":836239,"sequence":1,"start":"2023-09-13T10:10:01.000Z","end":"2023-09-13T15:10:01.000Z","timezone":"UTC","stamp":"2023-09-13T10:10:01.000Z","timestamp":"2023-09-13T10:10:01.000Z","summary":"Semifinal 1: IGY vs MAX","attendees":[],"alarms":[],"categories":[]},{"id":836238,"uid":836238,"sequence":1,"start":"2023-09-12T10:07:04.000Z","end":"2023-09-12T15:07:04.000Z","timezone":"UTC","stamp":"2023-09-12T10:07:04.000Z","timestamp":"2023-09-12T10:07:04.000Z","summary":"Quarterfinal 4: HLE vs FPB","attendees":[],"alarms":[],"categories":[]},{"id":836237,"uid":836237,"sequence":1,"start":"2023-09-11T10:06:41.000Z","end":"2023-09-11T15:06:41.000Z","timezone":"UTC","stamp":"2023-09-11T10:06:41.000Z","timestamp":"2023-09-11T10:06:41.000Z","summary":"Quarterfinal 3: DRX.C vs DK.C","attendees":[],"alarms":[],"categories":[]},{"id":836236,"uid":836236,"sequence":1,"start":"2023-09-10T10:06:44.000Z","end":"2023-09-10T15:06:44.000Z","timezone":"UTC","stamp":"2023-09-10T10:06:44.000Z","timestamp":"2023-09-10T10:06:44.000Z","summary":"Quarterfinal 2: MAX vs MJ","attendees":[],"alarms":[],"categories":[]},{"id":836235,"uid":836235,"sequence":1,"start":"2023-09-09T10:07:28.000Z","end":"2023-09-09T15:07:28.000Z","timezone":"UTC","stamp":"2023-09-09T10:07:28.000Z","timestamp":"2023-09-09T10:07:28.000Z","summary":"Quarterfinal 1: NS.EA vs IGY","attendees":[],"alarms":[],"categories":[]},{"id":836220,"uid":836220,"sequence":1,"start":"2023-09-08T12:21:20.000Z","end":"2023-09-08T13:21:20.000Z","timezone":"UTC","stamp":"2023-09-08T12:21:20.000Z","timestamp":"2023-09-08T12:21:20.000Z","summary":"Taipei Bravo vs Baby Whales","attendees":[],"alarms":[],"categories":[]},{"id":836219,"uid":836219,"sequence":1,"start":"2023-09-08T11:21:55.000Z","end":"2023-09-08T12:21:55.000Z","timezone":"UTC","stamp":"2023-09-08T11:21:55.000Z","timestamp":"2023-09-08T11:21:55.000Z","summary":"NS.EA vs FPB","attendees":[],"alarms":[],"categories":[]},{"id":836218,"uid":836218,"sequence":1,"start":"2023-09-08T10:26:15.000Z","end":"2023-09-08T11:26:15.000Z","timezone":"UTC","stamp":"2023-09-08T10:26:15.000Z","timestamp":"2023-09-08T10:26:15.000Z","summary":"FPB vs Taipei Bravo","attendees":[],"alarms":[],"categories":[]},{"id":836217,"uid":836217,"sequence":1,"start":"2023-09-08T09:33:58.000Z","end":"2023-09-08T10:33:58.000Z","timezone":"UTC","stamp":"2023-09-08T09:33:58.000Z","timestamp":"2023-09-08T09:33:58.000Z","summary":"Baby Whales vs NS.EA","attendees":[],"alarms":[],"categories":[]},{"id":1037756,"uid":1037756,"sequence":1,"start":"2024-09-11T07:00:00.000Z","end":"2024-09-11T10:00:00.000Z","timezone":"UTC","stamp":"2024-09-11T07:00:00.000Z","timestamp":"2024-09-11T07:00:00.000Z","summary":"Lower bracket final: BLGJ vs BWH","attendees":[],"alarms":[],"categories":[]},{"id":1037750,"uid":1037750,"sequence":1,"start":"2024-09-11T10:00:00.000Z","end":"2024-09-11T13:00:00.000Z","timezone":"UTC","stamp":"2024-09-11T10:00:00.000Z","timestamp":"2024-09-11T10:00:00.000Z","summary":"Lower bracket final: IMP vs LGDY","attendees":[],"alarms":[],"categories":[]},{"id":1037738,"uid":1037738,"sequence":1,"start":"2024-09-11T10:00:00.000Z","end":"2024-09-11T13:00:00.000Z","timezone":"UTC","stamp":"2024-09-11T10:00:00.000Z","timestamp":"2024-09-11T10:00:00.000Z","summary":"3rd place match: TBD vs TBD","attendees":[],"alarms":[],"categories":[]},{"id":1037741,"uid":1037741,"sequence":1,"start":"2024-09-11T13:00:00.000Z","end":"2024-09-11T16:00:00.000Z","timezone":"UTC","stamp":"2024-09-11T13:00:00.000Z","timestamp":"2024-09-11T13:00:00.000Z","summary":"Lower bracket final: MAX vs FAKA","attendees":[],"alarms":[],"categories":[]},{"id":1037749,"uid":1037749,"sequence":1,"start":"2024-09-12T07:00:00.000Z","end":"2024-09-12T10:00:00.000Z","timezone":"UTC","stamp":"2024-09-12T07:00:00.000Z","timestamp":"2024-09-12T07:00:00.000Z","summary":"3rd place match: TBD vs TBD","attendees":[],"alarms":[],"categories":[]},{"id":1037757,"uid":1037757,"sequence":1,"start":"2024-09-12T13:00:00.000Z","end":"2024-09-12T16:00:00.000Z","timezone":"UTC","stamp":"2024-09-12T13:00:00.000Z","timestamp":"2024-09-12T13:00:00.000Z","summary":"3rd place match: TBD vs TBD","attendees":[],"alarms":[],"categories":[]},{"id":1037812,"uid":1037812,"sequence":1,"start":"2024-09-14T07:00:00.000Z","end":"2024-09-14T10:00:00.000Z","timezone":"UTC","stamp":"2024-09-14T07:00:00.000Z","timestamp":"2024-09-14T07:00:00.000Z","summary":"TBD vs TBD","attendees":[],"alarms":[],"categories":[]},{"id":1037813,"uid":1037813,"sequence":1,"start":"2024-09-14T10:00:00.000Z","end":"2024-09-14T13:00:00.000Z","timezone":"UTC","stamp":"2024-09-14T10:00:00.000Z","timestamp":"2024-09-14T10:00:00.000Z","summary":"TBD vs TBD","attendees":[],"alarms":[],"categories":[]},{"id":1037814,"uid":1037814,"sequence":1,"start":"2024-09-14T13:00:00.000Z","end":"2024-09-14T16:00:00.000Z","timezone":"UTC","stamp":"2024-09-14T13:00:00.000Z","timestamp":"2024-09-14T13:00:00.000Z","summary":"TBD vs TBD","attendees":[],"alarms":[],"categories":[]},{"id":1037763,"uid":1037763,"sequence":1,"start":"2024-09-17T07:00:00.000Z","end":"2024-09-17T12:00:00.000Z","timezone":"UTC","stamp":"2024-09-17T07:00:00.000Z","timestamp":"2024-09-17T07:00:00.000Z","summary":"Upper bracket quarterfinal 1: TBD vs TBD","attendees":[],"alarms":[],"categories":[]},{"id":1037764,"uid":1037764,"sequence":1,"start":"2024-09-18T07:00:00.000Z","end":"2024-09-18T12:00:00.000Z","timezone":"UTC","stamp":"2024-09-18T07:00:00.000Z","timestamp":"2024-09-18T07:00:00.000Z","summary":"Upper bracket quarterfinal 2: TBD vs TBD","attendees":[],"alarms":[],"categories":[]},{"id":1037766,"uid":1037766,"sequence":1,"start":"2024-09-19T07:00:00.000Z","end":"2024-09-19T12:00:00.000Z","timezone":"UTC","stamp":"2024-09-19T07:00:00.000Z","timestamp":"2024-09-19T07:00:00.000Z","summary":"Upper bracket final: TBD vs TBD","attendees":[],"alarms":[],"categories":[]},{"id":1037765,"uid":1037765,"sequence":1,"start":"2024-09-20T07:00:00.000Z","end":"2024-09-20T12:00:00.000Z","timezone":"UTC","stamp":"2024-09-20T07:00:00.000Z","timestamp":"2024-09-20T07:00:00.000Z","summary":"Lower bracket semifinal: TBD vs TBD","attendees":[],"alarms":[],"categories":[]},{"id":1037767,"uid":1037767,"sequence":1,"start":"2024-09-21T07:00:00.000Z","end":"2024-09-21T12:00:00.000Z","timezone":"UTC","stamp":"2024-09-21T07:00:00.000Z","timestamp":"2024-09-21T07:00:00.000Z","summary":"Lower bracket final: TBD vs TBD","attendees":[],"alarms":[],"categories":[]},{"id":1037768,"uid":1037768,"sequence":1,"start":"2024-09-22T07:00:00.000Z","end":"2024-09-22T12:00:00.000Z","timezone":"UTC","stamp":"2024-09-22T07:00:00.000Z","timestamp":"2024-09-22T07:00:00.000Z","summary":"Grand final: TBD vs TBD","attendees":[],"alarms":[],"categories":[]}]}